CHANGELOG.txt
LICENSE.txt
MANIFEST.in
README.txt
setup.py
drew/__init__.py
drew.egg-info/PKG-INFO
drew.egg-info/SOURCES.txt
drew.egg-info/dependency_links.txt
drew.egg-info/top_level.txt
drew/Audio/stayinAlive.wav
drew/Frames/1.txt
drew/Frames/2.txt
drew/Frames/3.txt
drew/Frames/4.txt