Metadata-Version: 1.1
Name: drew
Version: 0.0.11
Summary: drew
Home-page: UNKNOWN
Author: Drew Summy
Author-email: dtsummy@gmail.com
License: MIT
Platform: UNKNOWN
Classifier: Development Status :: 5 - Production/Stable
Classifier: Intended Audience :: Education
Classifier: Operating System :: Microsoft :: Windows :: Windows 10
Classifier: License :: OSI Approved :: MIT License
Classifier: Programming Language :: Python :: 3
